jsonable_platform/__init__.py
jsonable_platform/core.py
jsonable_platform/shared.py
jsonable_platform/type.py
jsonable_platform-0.0.4.20240324123217.dist-info/LICENSE
jsonable_platform-0.0.4.20240324123217.dist-info/METADATA
jsonable_platform-0.0.4.20240324123217.dist-info/WHEEL
jsonable_platform-0.0.4.20240324123217.dist-info/RECORD
