Metadata-Version: 2.1
Name: jsonable-platform
Version: 0.0.4.20240324123217
Summary: Customizing convert to JSON from the objects you defined for Python 3+
Home-page: https://github.com/Lovemilk-Inc/jsonable-platform
License: BSD-3-Clause
Author: lovemilk
Author-email: zhuhansan666@outlook.com
Requires-Python: >=3.9,<4.0
Classifier: License :: OSI Approved :: BSD License
Classifier: Operating System :: Microsoft :: Windows
Classifier: Operating System :: POSIX
Classifier: Programming Language :: Python
Classifier: Programming Language :: Python :: 3
Classifier: Programming Language :: Python :: 3.9
Classifier: Programming Language :: Python :: 3.10
Classifier: Programming Language :: Python :: 3.11
Classifier: Programming Language :: Python :: 3.12
Classifier: Programming Language :: Python :: 3.13
Classifier: Topic :: File Formats :: JSON
Requires-Dist: typing_extensions ; python_version < "3.11"
Project-URL: Repository, https://github.com/Lovemilk-Inc/jsonable-platform.git
